README.md
setup.py
yellowpages_search_results_scraper/__init__.py
yellowpages_search_results_scraper.egg-info/PKG-INFO
yellowpages_search_results_scraper.egg-info/SOURCES.txt
yellowpages_search_results_scraper.egg-info/dependency_links.txt
yellowpages_search_results_scraper.egg-info/requires.txt
yellowpages_search_results_scraper.egg-info/top_level.txt