Metadata-Version: 2.1
Name: yellowpages-search-results-scraper
Version: 1.0.0
Summary: A python library to search keyword and scrape search results data from yellowpages.
Home-page: https://datakund.com
Author: DataKund
Author-email: datakund@gmail.com
License: Apache License 2.0
Keywords: yellowpages python bot_studio scraper web-scraping business search-results search keyword
Platform: UNKNOWN
